tiny_thermal_camera.cpython-310-x86_64-linux-gnu.so
tiny_thermal_camera.py
tiny_thermal_camera.libs/libpcre2-8-516f4c9d.so.0.7.1
tiny_thermal_camera.libs/libselinux-64a010fa.so.1
tiny_thermal_camera.libs/libudev-6ca67360.so.1.6.11
tiny_thermal_camera.libs/libblkid-b1e34c65.so.1.1.0
tiny_thermal_camera.libs/libuuid-6395f7d6.so.1.3.0
tiny_thermal_camera.libs/libusb-1-1b307d35.0.so.0.2.0
tiny_thermal_camera.libs/libmount-02901b63.so.1.1.0
tiny_thermal_camera-1.0.0.dist-info/WHEEL
tiny_thermal_camera-1.0.0.dist-info/RECORD
tiny_thermal_camera-1.0.0.dist-info/top_level.txt
tiny_thermal_camera-1.0.0.dist-info/METADATA
tiny_thermal_camera-1.0.0.dist-info/licenses/LICENSE
