Metadata-Version: 2.1
Name: tiny-thermal-camera
Version: 1.0.0
Summary: Python bindings for P2/Tiny1C thermal camera SDK
Author-email: Thermal Camera SDK <mail@matbee.com>
License: MIT License
Project-URL: Homepage, https://github.com/matbeedotcom/Tiny-1C-Python-Bindings
Project-URL: Documentation, https://github.com/matbeedotcom/Tiny-1C-Python-Bindings/blob/main/README.md
Project-URL: Repository, https://github.com/matbeedotcom/Tiny-1C-Python-Bindings.git
Project-URL: Bug Tracker, https://github.com/matbeedotcom/Tiny-1C-Python-Bindings/issues
Keywords: thermal,camera,temperature,imaging,P2,Tiny1C
Classifier: Development Status :: 4 - Beta
Classifier: Intended Audience :: Developers
Classifier: Intended Audience :: Science/Research
Classifier: Operating System :: POSIX :: Linux
Classifier: Operating System :: Microsoft :: Windows
Classifier: Programming Language :: C++
Classifier: Programming Language :: Python :: 3
Classifier: Programming Language :: Python :: 3.6
Classifier: Programming Language :: Python :: 3.7
Classifier: Programming Language :: Python :: 3.8
Classifier: Programming Language :: Python :: 3.9
Classifier: Programming Language :: Python :: 3.10
Classifier: Programming Language :: Python :: 3.11
Classifier: Programming Language :: Python :: 3.12
Classifier: Topic :: Scientific/Engineering
Classifier: Topic :: Scientific/Engineering :: Image Processing
Classifier: Topic :: Software Development :: Libraries :: Python Modules
Requires-Python: >=3.6
License-File: LICENSE
Requires-Dist: numpy>=1.15.0
Provides-Extra: all
Requires-Dist: tiny-thermal-camera[dev,visualization]; extra == "all"
Provides-Extra: dev
Requires-Dist: pytest>=6.0; extra == "dev"
Requires-Dist: black; extra == "dev"
Requires-Dist: flake8; extra == "dev"
Requires-Dist: mypy; extra == "dev"
Provides-Extra: visualization
Requires-Dist: opencv-python>=4.0.0; extra == "visualization"
Requires-Dist: matplotlib>=3.0.0; extra == "visualization"
